[
  {
    "profile": "buyer_1",
    "name": "Aitor",
    "surname": "López",
    "birth_date": "1996-08-10",
    "dni": "62293809B",
    "email": "aitor.lópez@supercode.com",
    "password": "454855",
    "city": "Bilbao",
    "iban": "ES64209594302468297506",
    "assets": 3960.35
  },
  {
    "profile": "buyer_2",
    "name": "Aitxiber",
    "surname": "Beitia",
    "birth_date": "1984-09-05",
    "dni": "05418980L",
    "email": "aitxiber.beitia@superpixel.net",
    "password": "651317",
    "city": "Gernika",
    "iban": "ES78209515526414444232",
    "assets": 2505.44
  },
  {
    "profile": "buyer_3",
    "name": "Ana",
    "surname": "Etxebarria",
    "birth_date": "1989-08-23",
    "dni": "12274618R",
    "email": "ana.etxebarria@extremecode.tech",
    "password": "674283",
    "city": "Vitoria-Gasteiz",
    "iban": "ES46209509669691508330",
    "assets": 7149.77
  },
  {
    "profile": "buyer_4",
    "name": "Marc",
    "surname": "Andreu",
    "birth_date": "1974-05-23",
    "dni": "26261009T",
    "email": "marc.andreu@superpixel.net",
    "password": "335735",
    "city": "Barcelona",
    "iban": "ES95209557228756668831",
    "assets": 5864.18
  },
  {
    "profile": "buyer_5",
    "name": "Sara",
    "surname": "Urkiaga",
    "birth_date": "1994-03-12",
    "dni": "68578114A",
    "email": "sara.urkiaga@brilliantdev.com",
    "password": "407760",
    "city": "Plentzia",
    "iban": "ES29209582310567369996",
    "assets": 1504.82
  },
  {
    "profile": "buyer_6",
    "name": "Manuel",
    "surname": "Díez",
    "birth_date": "1979-02-14",
    "dni": "81701114P",
    "email": "manuel.díez@cleverbyte.site",
    "password": "416426",
    "city": "Valladolid",
    "iban": "ES66209515849599482112",
    "assets": 1115.56
  },
  {
    "profile": "buyer_7",
    "name": "Agurtzane",
    "surname": "Laka",
    "birth_date": "1968-12-31",
    "dni": "22158130E",
    "email": "agurtzane.laka@hyperbyte.online",
    "password": "417927",
    "city": "Bilbao",
    "iban": "ES35209545823093578942",
    "assets": 7426.41
  },
  {
    "profile": "buyer_8",
    "name": "Patxi",
    "surname": "Urrutia",
    "birth_date": "1979-04-04",
    "dni": "92963253J",
    "email": "patxi.urrutia@cooldata.org",
    "password": "249997",
    "city": "Durango",
    "iban": "ES23209537262094639345",
    "assets": 1926.45
  }
]