[
  {
    "profile": "buyer_1",
    "name": "Luis",
    "surname": "Garay",
    "birth_date": "1996-08-10",
    "dni": "83800682K",
    "email": "luis.garay@smartdev.tech",
    "password": "084973",
    "city": "Bilbao",
    "iban": "ES03209554921006909146",
    "assets": 4932.99
  },
  {
    "profile": "buyer_2",
    "name": "Carmen",
    "surname": "Lozano",
    "birth_date": "1984-09-05",
    "dni": "77271333G",
    "email": "carmen.lozano@extremetech.online",
    "password": "202796",
    "city": "Zarautz",
    "iban": "ES68209544164627199744",
    "assets": 2120.92
  },
  {
    "profile": "buyer_3",
    "name": "Ana",
    "surname": "Piñeiro",
    "birth_date": "1989-08-23",
    "dni": "02722604W",
    "email": "ana.piñeiro@awesomepixel.online",
    "password": "284038",
    "city": "Amurrio",
    "iban": "ES51209583314867248115",
    "assets": 6086.71
  },
  {
    "profile": "buyer_4",
    "name": "Jorge",
    "surname": "Moreno",
    "birth_date": "1974-05-23",
    "dni": "70577394P",
    "email": "jorge.moreno@supertech.net",
    "password": "669819",
    "city": "Galdakao",
    "iban": "ES87209546928226892835",
    "assets": 5552.42
  },
  {
    "profile": "buyer_5",
    "name": "Sara",
    "surname": "Gurrutxaga",
    "birth_date": "1994-03-12",
    "dni": "95051607J",
    "email": "sara.gurrutxaga@brilliantpixel.site",
    "password": "618243",
    "city": "Donostia",
    "iban": "ES83209588162793831702",
    "assets": 1453.33
  },
  {
    "profile": "buyer_6",
    "name": "Manuel",
    "surname": "Rodríguez",
    "birth_date": "1979-02-14",
    "dni": "52748360E",
    "email": "manuel.rodríguez@hyperapp.digital",
    "password": "587381",
    "city": "Vitoria-Gasteiz",
    "iban": "ES44209565041954830314",
    "assets": 1690.49
  },
  {
    "profile": "buyer_7",
    "name": "María",
    "surname": "Valdec",
    "birth_date": "1968-12-31",
    "dni": "57590201H",
    "email": "maría.valdec@ultraapp.org",
    "password": "070777",
    "city": "Portugalete",
    "iban": "ES66209579843299010558",
    "assets": 1835.91
  },
  {
    "profile": "buyer_8",
    "name": "Antonio",
    "surname": "Miranda",
    "birth_date": "1979-04-04",
    "dni": "72219694Q",
    "email": "antonio.miranda@awesomecode.online",
    "password": "656430",
    "city": "Labastida",
    "iban": "ES24209502580516639144",
    "assets": 1691.88
  }
]